xingzuo_luck/__init__.py
xingzuo_luck/xingzuo_luck.py
xingzuo_luck-1.0.0.dist-info/LICENSE
xingzuo_luck-1.0.0.dist-info/METADATA
xingzuo_luck-1.0.0.dist-info/WHEEL
xingzuo_luck-1.0.0.dist-info/RECORD
