Metadata-Version: 2.1
Name: xingzuo-luck
Version: 1.0.0
Summary: 
License: MIT
Author: mengxinyuan
Author-email: 1648576390@qq.com
Requires-Python: >=3.8,<4.0
Classifier: License :: OSI Approved :: MIT License
Classifier: Programming Language :: Python :: 3
Classifier: Programming Language :: Python :: 3.8
Classifier: Programming Language :: Python :: 3.9
Classifier: Programming Language :: Python :: 3.10
Classifier: Programming Language :: Python :: 3.11
